Metadata-Version: 2.4
Name: tree3
Version: 0.2.0
Summary: A command line utility to display and create directory structures
Author-email: Amir Mazinani <info.mazinani@gmail.com>
License: MIT
Project-URL: Homepage, https://github.com/amirmazinani/tree3
Project-URL: Bug Tracker, https://github.com/amirmazinani/tree3/issues
Keywords: tree,parsing,python,data structure
Classifier: Programming Language :: Python :: 3
Classifier: License :: OSI Approved :: MIT License
Classifier: Operating System :: OS Independent
Requires-Python: >=3.6
License-File: LICENSE
Dynamic: license-file
